geocoding/__init__.py
geocoding/core/__init__.py
geocoding/core/dubious_marker.py
geocoding/core/exceptions.py
geocoding/core/geocoder.py
geocoding/core/utils.py
geocoding/core/yandex_modified.py
geocoding/scripts/__init__.py
geocoding/scripts/correct_dubious_geo.py
geocoding/scripts/geocode.py
geocoding/scripts/update_market_deals.py
preprocessing/__init__.py
preprocessing/cli/__init__.py
preprocessing/cli/preprocess_deals.py
preprocessing/cli/preprocess_houses.py
preprocessing/core/__init__.py
preprocessing/core/features.py
preprocessing/core/houses.py
preprocessing/core/preprocessing.py
preprocessing/core/utils.py
s4b_data_processing-0.3.0.dist-info/METADATA
s4b_data_processing-0.3.0.dist-info/WHEEL
s4b_data_processing-0.3.0.dist-info/entry_points.txt
s4b_data_processing-0.3.0.dist-info/top_level.txt
s4b_data_processing-0.3.0.dist-info/RECORD
