Metadata-Version: 2.4
Name: s4b-data-processing
Version: 0.3.0
Summary: Utilities for geocoding and preprocessing real estate data
Author: Unknown
Requires-Python: >=3.10
Requires-Dist: pandas==2.2.3
Requires-Dist: numpy==2.2.6
Requires-Dist: plotly==6.1.2
Requires-Dist: tqdm==4.67.1
Requires-Dist: shapely==2.1.1
Requires-Dist: geopy==2.4.1
Requires-Dist: requests==2.32.3
Requires-Dist: geopandas==1.1.0
Requires-Dist: transliterate==1.10.2
Requires-Dist: openpyxl==3.1.5
Requires-Dist: pyarrow==20.0.0
Requires-Dist: fastparquet==2024.11.0
